ipwb/__init__.py
ipwb/__main__.py
ipwb/backends.py
ipwb/error_handler.py
ipwb/exceptions.py
ipwb/indexer.py
ipwb/replay.py
ipwb/settings.py
ipwb/util.py
ipwb/assets/admin.css
ipwb/assets/daemonController.js
ipwb/assets/logo.png
ipwb/assets/reconstructive-banner.js
ipwb/assets/reconstructive.js
ipwb/assets/serviceWorker.js
ipwb/assets/webui.css
ipwb/assets/webui.js
ipwb/assets/favicons/android-chrome-192x192.png
ipwb/assets/favicons/apple-touch-icon.png
ipwb/assets/favicons/browserconfig.xml
ipwb/assets/favicons/favicon-16x16.png
ipwb/assets/favicons/favicon-32x32.png
ipwb/assets/favicons/favicon.ico
ipwb/assets/favicons/manifest.json
ipwb/assets/favicons/mstile-150x150.png
ipwb/assets/favicons/safari-pinned-tab.svg
ipwb/templates/admin.html
ipwb/templates/index.html
ipwb-0.2024.10.24.1853.dist-info/LICENSE
ipwb-0.2024.10.24.1853.dist-info/METADATA
ipwb-0.2024.10.24.1853.dist-info/WHEEL
ipwb-0.2024.10.24.1853.dist-info/entry_points.txt
ipwb-0.2024.10.24.1853.dist-info/top_level.txt
ipwb-0.2024.10.24.1853.dist-info/RECORD
