Metadata-Version: 2.1
Name: ipwb
Version: 0.2024.10.24.1853
Summary: InterPlanetary Wayback (ipwb): Web Archive integration with IPFS
Home-page: https://github.com/oduwsdl/ipwb
Download-URL: https://github.com/oduwsdl/ipwb
Author: Mat Kelly
Author-email: me@matkelly.com
License: MIT
Keywords: http web archives ipfs distributed odu wayback memento
Classifier: Development Status :: 4 - Beta
Classifier: Environment :: Web Environment
Classifier: Programming Language :: Python :: 3.9
Classifier: Programming Language :: Python :: 3.10
Classifier: Programming Language :: Python :: 3.11
Classifier: Programming Language :: Python :: 3.12
Classifier: Programming Language :: Python :: 3.13
Classifier: License :: OSI Approved :: MIT License
Classifier: Intended Audience :: Developers
Classifier: Intended Audience :: Information Technology
Classifier: Intended Audience :: Science/Research
Classifier: Topic :: Internet :: WWW/HTTP
Classifier: Topic :: System :: Archiving
Classifier: Topic :: System :: Archiving :: Backup
Classifier: Topic :: System :: Archiving :: Mirroring
Classifier: Topic :: Utilities
Provides: ipwb
Requires-Python: >=3.9
License-File: LICENSE
Requires-Dist: warcio>=1.5.3
Requires-Dist: ipfshttpclient>=0.8.0a
Requires-Dist: Flask>=3.0
Requires-Dist: pycryptodome>=3.4.11
Requires-Dist: requests>=2.19.1
Requires-Dist: beautifulsoup4>=4.6.3
Requires-Dist: surt>=0.3.0
